pygidb/__init__.py
pygidb/constants.py
pygidb/pygidb.py
pygidb/types/achievements.py
pygidb/types/adventureranks.py
pygidb/types/animals.py
pygidb/types/api.py
pygidb/types/artifacts.py
pygidb/types/characters.py
pygidb/types/crafts.py
pygidb/types/domains.py
pygidb/types/elements.py
pygidb/types/enemies.py
pygidb/types/foods.py
pygidb/types/geographies.py
pygidb/types/gliders.py
pygidb/types/materials.py
pygidb/types/namecards.py
pygidb/types/outfits.py
pygidb/types/talentmaterialtypes.py
pygidb/types/tcg.py
pygidb/types/weaponmaterialtypes.py
pygidb/types/weapons.py
pygidb-0.0.1a0.dist-info/LICENSE
pygidb-0.0.1a0.dist-info/METADATA
pygidb-0.0.1a0.dist-info/WHEEL
pygidb-0.0.1a0.dist-info/top_level.txt
pygidb-0.0.1a0.dist-info/RECORD
